{"type":"FeatureCollection","features":[{"type":"Feature","id":0,"title":"Blue Tokai, Mahalaxmi, Mumbai","properties":{"marker-color":"#1e00ff","marker-size":"medium","marker-symbol":"circle"},"geometry":{"type":"Point","coordinates":[72.8252175450325,18.989393157200194]}},{"type":"Feature","id":1,"title":"Celestia Spaces, Sewri West, Mumbai","properties":{"marker-color":"#1e00ff","marker-size":"medium","marker-symbol":"circle"},"geometry":{"type":"Point","coordinates":[72.84848034381866,18.993376274570153]}}]}